IHpip/__init__.py
IHpip-0.1.0.dist-info/METADATA
IHpip-0.1.0.dist-info/WHEEL
IHpip-0.1.0.dist-info/entry_points.txt
IHpip-0.1.0.dist-info/top_level.txt
IHpip-0.1.0.dist-info/RECORD
