Metadata-Version: 2.1
Name: IHpip
Version: 0.1.0
Summary: Small package that makes requirement.txt files better
Home-page: https://gitlab.com/ire4ever1190/ihpip
Author: Jake Leahy
Author-email: darhyaust@gmail.com
License: UNKNOWN
Platform: UNKNOWN
